nipd/__init__.py
nipd/agent_simulator.py
nipd/network_environment.py
nipd/network_tops.py
nipd/round.py
nipd/models/__init__.py
nipd/models/decentralized_ppo/__init__.py
nipd/models/decentralized_ppo/decentralized_ppo_agent.py
nipd/models/decentralized_ppo/decentralized_ppo_trainer.py
nipd/models/decentralized_ppo/decentralized_ppo_wrapper.py
nipd/models/decentralized_ppo/decentralized_ppo_models/decentralized_ppo_agent_0_final.pt
nipd/models/decentralized_ppo/decentralized_ppo_models/decentralized_ppo_agent_1_final.pt
nipd/models/decentralized_ppo/decentralized_ppo_models/decentralized_ppo_agent_2_final.pt
nipd/models/decentralized_ppo/decentralized_ppo_models/decentralized_ppo_agent_3_final.pt
nipd/models/decentralized_ppo/decentralized_ppo_models/decentralized_ppo_agent_4_final.pt
nipd/models/decentralized_ppo/decentralized_ppo_models/decentralized_ppo_agent_5_final.pt
nipd/models/decentralized_ppo/decentralized_ppo_models/decentralized_ppo_agent_6_final.pt
nipd/models/decentralized_ppo/decentralized_ppo_models/decentralized_ppo_agent_7_final.pt
nipd/models/decentralized_ppo/decentralized_ppo_models/decentralized_ppo_agent_8_final.pt
nipd/models/decentralized_ppo/decentralized_ppo_models/decentralized_ppo_agent_9_final.pt
nipd/models/lola/__init__.py
nipd/models/lola/lola_agent.py
nipd/models/lola/lola_environment.py
nipd/models/lola/lola_trainer.py
nipd/models/lola/lola_models/final_lola_agents/lola_agent_0_final.pt
nipd/models/lola/lola_models/final_lola_agents/lola_agent_1_final.pt
nipd/models/lola/lola_models/final_lola_agents/lola_agent_2_final.pt
nipd/models/lola/lola_models/final_lola_agents/lola_agent_3_final.pt
nipd/models/lola/lola_models/final_lola_agents/lola_agent_4_final.pt
nipd/models/lola/lola_models/final_lola_agents/lola_agent_5_final.pt
nipd/models/lola/lola_models/final_lola_agents/lola_agent_6_final.pt
nipd/models/lola/lola_models/final_lola_agents/lola_agent_7_final.pt
nipd/models/lola/lola_models/final_lola_agents/lola_agent_8_final.pt
nipd_framework-1.0.0.dist-info/licenses/LICENSE
nipd_framework-1.0.0.dist-info/METADATA
nipd_framework-1.0.0.dist-info/WHEEL
nipd_framework-1.0.0.dist-info/entry_points.txt
nipd_framework-1.0.0.dist-info/top_level.txt
nipd_framework-1.0.0.dist-info/RECORD
