Metadata-Version: 2.4
Name: nipd-framework
Version: 1.0.0
Summary: Network Iterated Prisoner's Dilemma Framework for Multi-Agent Learning
Home-page: https://github.com/maximusJWL/nipd-framework
Author: maximusjwl
Author-email: max.lams99@gmail.com
License: CC BY-NC 4.0
Project-URL: Bug Reports, https://github.com/maximusJWL/nipd-framework/issues
Project-URL: Source, https://github.com/maximusJWL/nipd-framework
Project-URL: Documentation, https://github.com/maximusJWL/nipd-framework#readme
Keywords: multi-agent,prisoner-dilemma,reinforcement-learning,game-theory,networks,cooperation,defection,social-dilemmas
Classifier: Intended Audience :: Science/Research
Classifier: Intended Audience :: Education
Classifier: License :: Other/Proprietary License
Classifier: Operating System :: OS Independent
Classifier: Programming Language :: Python :: 3
Classifier: Programming Language :: Python :: 3.13
Classifier: Topic :: Scientific/Engineering :: Artificial Intelligence
Classifier: Topic :: Scientific/Engineering :: Mathematics
Requires-Python: >=3.13
License-File: LICENSE
Requires-Dist: numpy>=1.21.0
Requires-Dist: matplotlib>=3.5.0
Requires-Dist: torch>=1.9.0
Requires-Dist: tqdm>=4.62.0
Requires-Dist: pandas>=1.3.0
Requires-Dist: seaborn>=0.11.0
Requires-Dist: networkx>=2.6.0
Requires-Dist: ipykernel>=6.0.0
Requires-Dist: jupyter>=1.0.0
Requires-Dist: notebook>=6.4.0
Provides-Extra: dev
Requires-Dist: pytest>=6.0; extra == "dev"
Requires-Dist: pytest-cov>=2.0; extra == "dev"
Requires-Dist: black>=21.0; extra == "dev"
Requires-Dist: flake8>=3.8; extra == "dev"
Requires-Dist: mypy>=0.800; extra == "dev"
Provides-Extra: docs
Requires-Dist: sphinx>=4.0; extra == "docs"
Requires-Dist: sphinx-rtd-theme>=1.0; extra == "docs"
Dynamic: author
Dynamic: author-email
Dynamic: classifier
Dynamic: description
Dynamic: description-content-type
Dynamic: home-page
Dynamic: keywords
Dynamic: license
Dynamic: license-file
Dynamic: project-url
Dynamic: provides-extra
Dynamic: requires-dist
Dynamic: requires-python
Dynamic: summary
